kad2gp/__init__.py
kad2gp/converter.py
kad2gp/logger.py
kad2gp/main_converter.py
kad2gp/main_gui.py
kad2gp/tools.py
kad2gp-0.2.dist-info/METADATA
kad2gp-0.2.dist-info/WHEEL
kad2gp-0.2.dist-info/entry_points.txt
kad2gp-0.2.dist-info/top_level.txt
kad2gp-0.2.dist-info/RECORD
