Metadata-Version: 2.1
Name: kad2gp
Version: 0.2
Summary: Converts http://pkk.rosreestr.ru to Garden Planner's file.
Home-page: https://github.com/TonSilver/kad2gp
Author: Anton Serebryakov
Author-email: serebryakov.anton@gmail.com
License: UNKNOWN
Platform: UNKNOWN
Classifier: Programming Language :: Python :: 3
Classifier: License :: OSI Approved :: MIT License
Classifier: Operating System :: OS Independent
Requires-Dist: rosreestr2coord
Requires-Dist: opencv-python
